{
  "valid": true,
  "simulation_case": "nasa_44344_validation",
  "wall_thermal_mode": "adiabatic",
  "objective": {
    "eta_bar": 0.48143119797368716,
    "protected_eta_bar": 0.5660571734315004,
    "protected_area_m2": 0.0012319188021315119
  },
  "constraints": {
    "coolant_mass_flow_ratio": 0.9999982622759378,
    "coolant_actual_kg_s": 0.005320266354829073,
    "mass_imbalance": -2.8265640131274784e-07,
    "pressure_loss": {
      "definition": "diagnostic_delta_p0 = mean(total-pressure on inlet) - mean(total-pressure on outlet)",
      "delta_total_pressure_Pa": 98032.88220671847,
      "inlet_total_pressure_mean_Pa": 285129.6080977259,
      "outlet_total_pressure_mean_Pa": 187096.72589100743,
      "note": "Diagnostic only; final loss coefficient definition must be fixed before publication."
    },
    "y_plus_p95": 1.1070618629455566,
    "y_plus_max": 1.6195837259292603
  },
  "references": {
    "Tg_ref_K": 701.0,
    "Tc_ref": {
      "method": "coolant target mass-flow weighted",
      "value_K": 593.6263151083753,
      "components": [
        {
          "region": "suction",
          "total_temperature_K": 595.85,
          "weight_kg_s": 0.0026114173
        },
        {
          "region": "showerhead",
          "total_temperature_K": 602.86,
          "weight_kg_s": 0.0012433465
        },
        {
          "region": "pressure",
          "total_temperature_K": 581.83,
          "weight_kg_s": 0.0014655118
        }
      ]
    }
  },
  "diagnostics": {
    "selected_wall_surfaces": [
      "vane_wall"
    ],
    "all_wall_surfaces": [
      "film_hole_wall",
      "plenum_wall",
      "vane_wall"
    ],
    "available_scalar_fields": [
      "wall-temperature",
      "temperature",
      "y-plus"
    ],
    "available_heat_transfer_fields": [
      "heat-flux",
      "stanton-number",
      "heat-transfer-coef",
      "heat-transfer-coef-wall-adj",
      "wall-adjacent-temperature"
    ],
    "mass_flow_report_available": true,
    "convergence": {
      "available": true,
      "path": "E:\\Work\\BOfm\\fluent-20260715-182037-316152.trn",
      "warnings": {
        "artificial_wall": 0,
        "reversed_flow": 0,
        "divergence": 0,
        "floating_point": 0
      },
      "residual_row_count": 401,
      "last_residual_row": {
        "iteration": 1600,
        "continuity": 0.0011683,
        "x_velocity": 4.2384e-06,
        "y_velocity": 9.4341e-06,
        "z_velocity": 3.9483e-06,
        "energy": 4.7809e-05,
        "k": 0.00016115,
        "omega": 0.00094583
      }
    },
    "export_log": "E:\\Work\\BOfm\\runs\\nasa_44344\\fine\\post_iter1600\\export_workbench_film_results.log"
  }
}